[{"Key":{"x":0,"y":0},"Value":{"InfoAddress":0,"IsPlusMinusAmbit":false,"IsValidValue":false,"ItemBitPosition":0,"ItemByteOrder":1,"ItemDecimalBits":0,"ItemName":"年","ItemPlusMinusAmbit":0,"ItemPosition":0,"ItemShowType":0,"ItemSize":1,"ItemType":5,"ItemUnit":"","ItemValue":0,"SmsCode":"","SmsSendFilter":false}},{"Key":{"x":1,"y":0},"Value":{"InfoAddress":0,"IsPlusMinusAmbit":false,"IsValidValue":false,"ItemBitPosition":0,"ItemByteOrder":1,"ItemDecimalBits":0,"ItemName":"月","ItemPlusMinusAmbit":0,"ItemPosition":1,"ItemShowType":0,"ItemSize":1,"ItemType":5,"ItemUnit":"","ItemValue":0,"SmsCode":"","SmsSendFilter":false}},{"Key":{"x":2,"y":0},"Value":{"InfoAddress":0,"IsPlusMinusAmbit":false,"IsValidValue":false,"ItemBitPosition":0,"ItemByteOrder":1,"ItemDecimalBits":0,"ItemName":"日","ItemPlusMinusAmbit":0,"ItemPosition":2,"ItemShowType":0,"ItemSize":1,"ItemType":5,"ItemUnit":"","ItemValue":0,"SmsCode":"","SmsSendFilter":false}},{"Key":{"x":3,"y":0},"Value":{"InfoAddress":0,"IsPlusMinusAmbit":false,"IsValidValue":false,"ItemBitPosition":0,"ItemByteOrder":1,"ItemDecimalBits":0,"ItemName":"时","ItemPlusMinusAmbit":0,"ItemPosition":3,"ItemShowType":0,"ItemSize":1,"ItemType":5,"ItemUnit":"","ItemValue":0,"SmsCode":"","SmsSendFilter":false}},{"Key":{"x":4,"y":0},"Value":{"InfoAddress":0,"IsPlusMinusAmbit":false,"IsValidValue":false,"ItemBitPosition":0,"ItemByteOrder":1,"ItemDecimalBits":0,"ItemName":"分","ItemPlusMinusAmbit":0,"ItemPosition":4,"ItemShowType":0,"ItemSize":1,"ItemType":5,"ItemUnit":"","ItemValue":0,"SmsCode":"","SmsSendFilter":false}},{"Key":{"x":5,"y":0},"Value":{"InfoAddress":0,"IsPlusMinusAmbit":false,"IsValidValue":false,"ItemBitPosition":0,"ItemByteOrder":1,"ItemDecimalBits":0,"ItemName":"秒","ItemPlusMinusAmbit":0,"ItemPosition":5,"ItemShowType":0,"ItemSize":1,"ItemType":5,"ItemUnit":"","ItemValue":0,"SmsCode":"","SmsSendFilter":false}},{"Key":{"x":6,"y":0},"Value":{"InfoAddress":1,"IsPlusMinusAmbit":false,"IsValidValue":false,"ItemBitPosition":0,"ItemByteOrder":1,"ItemDecimalBits":0,"ItemName":"速断","ItemPlusMinusAmbit":0,"ItemPosition":6,"ItemShowType":0,"ItemSize":0,"ItemType":5,"ItemUnit":"","ItemValue":0,"SmsCode":"","SmsSendFilter":false}},{"Key":{"x":7,"y":0},"Value":{"InfoAddress":2,"IsPlusMinusAmbit":false,"IsValidValue":false,"ItemBitPosition":0,"ItemByteOrder":1,"ItemDecimalBits":0,"ItemName":"过流","ItemPlusMinusAmbit":0,"ItemPosition":7,"ItemShowType":0,"ItemSize":0,"ItemType":5,"ItemUnit":"","ItemValue":0,"SmsCode":"","SmsSendFilter":false}},{"Key":{"x":9,"y":0},"Value":{"InfoAddress":4,"IsPlusMinusAmbit":false,"IsValidValue":false,"ItemBitPosition":0,"ItemByteOrder":1,"ItemDecimalBits":0,"ItemName":"过负荷","ItemPlusMinusAmbit":0,"ItemPosition":9,"ItemShowType":0,"ItemSize":0,"ItemType":5,"ItemUnit":"","ItemValue":0,"SmsCode":"","SmsSendFilter":false}},{"Key":{"x":10,"y":0},"Value":{"InfoAddress":5,"IsPlusMinusAmbit":false,"IsValidValue":false,"ItemBitPosition":0,"ItemByteOrder":1,"ItemDecimalBits":0,"ItemName":"零序过流","ItemPlusMinusAmbit":0,"ItemPosition":10,"ItemShowType":0,"ItemSize":0,"ItemType":5,"ItemUnit":"","ItemValue":0,"SmsCode":"","SmsSendFilter":false}},{"Key":{"x":12,"y":0},"Value":{"InfoAddress":7,"IsPlusMinusAmbit":false,"IsValidValue":false,"ItemBitPosition":0,"ItemByteOrder":1,"ItemDecimalBits":0,"ItemName":"一次重合闸","ItemPlusMinusAmbit":0,"ItemPosition":12,"ItemShowType":0,"ItemSize":0,"ItemType":5,"ItemUnit":"","ItemValue":0,"SmsCode":"","SmsSendFilter":false}},{"Key":{"x":13,"y":0},"Value":{"InfoAddress":8,"IsPlusMinusAmbit":false,"IsValidValue":false,"ItemBitPosition":0,"ItemByteOrder":1,"ItemDecimalBits":0,"ItemName":"二次重合闸","ItemPlusMinusAmbit":0,"ItemPosition":13,"ItemShowType":0,"ItemSize":0,"ItemType":5,"ItemUnit":"","ItemValue":0,"SmsCode":"","SmsSendFilter":false}},{"Key":{"x":14,"y":0},"Value":{"InfoAddress":9,"IsPlusMinusAmbit":false,"IsValidValue":false,"ItemBitPosition":0,"ItemByteOrder":1,"ItemDecimalBits":0,"ItemName":"三次重合闸","ItemPlusMinusAmbit":0,"ItemPosition":14,"ItemShowType":0,"ItemSize":0,"ItemType":5,"ItemUnit":"","ItemValue":0,"SmsCode":"","SmsSendFilter":false}},{"Key":{"x":15,"y":0},"Value":{"InfoAddress":10,"IsPlusMinusAmbit":false,"IsValidValue":false,"ItemBitPosition":0,"ItemByteOrder":1,"ItemDecimalBits":0,"ItemName":"四次重合闸","ItemPlusMinusAmbit":0,"ItemPosition":15,"ItemShowType":0,"ItemSize":0,"ItemType":5,"ItemUnit":"","ItemValue":0,"SmsCode":"","SmsSendFilter":false}},{"Key":{"x":16,"y":0},"Value":{"InfoAddress":11,"IsPlusMinusAmbit":false,"IsValidValue":false,"ItemBitPosition":0,"ItemByteOrder":1,"ItemDecimalBits":0,"ItemName":"定值错","ItemPlusMinusAmbit":0,"ItemPosition":16,"ItemShowType":0,"ItemSize":0,"ItemType":5,"ItemUnit":"","ItemValue":0,"SmsCode":"","SmsSendFilter":false}},{"Key":{"x":19,"y":0},"Value":{"InfoAddress":15,"IsPlusMinusAmbit":false,"IsValidValue":false,"ItemBitPosition":0,"ItemByteOrder":1,"ItemDecimalBits":0,"ItemName":"强制跳闸","ItemPlusMinusAmbit":0,"ItemPosition":19,"ItemShowType":0,"ItemSize":0,"ItemType":5,"ItemUnit":"","ItemValue":0,"SmsCode":"","SmsSendFilter":false}},{"Key":{"x":20,"y":0},"Value":{"InfoAddress":16,"IsPlusMinusAmbit":false,"IsValidValue":false,"ItemBitPosition":0,"ItemByteOrder":1,"ItemDecimalBits":0,"ItemName":"交流失电","ItemPlusMinusAmbit":0,"ItemPosition":20,"ItemShowType":0,"ItemSize":0,"ItemType":5,"ItemUnit":"","ItemValue":0,"SmsCode":"","SmsSendFilter":false}},{"Key":{"x":21,"y":0},"Value":{"InfoAddress":17,"IsPlusMinusAmbit":false,"IsValidValue":false,"ItemBitPosition":0,"ItemByteOrder":1,"ItemDecimalBits":0,"ItemName":"负序I段","ItemPlusMinusAmbit":0,"ItemPosition":21,"ItemShowType":0,"ItemSize":0,"ItemType":5,"ItemUnit":"","ItemValue":0,"SmsCode":"","SmsSendFilter":false}},{"Key":{"x":22,"y":0},"Value":{"InfoAddress":18,"IsPlusMinusAmbit":false,"IsValidValue":false,"ItemBitPosition":0,"ItemByteOrder":1,"ItemDecimalBits":0,"ItemName":"负序II段","ItemPlusMinusAmbit":0,"ItemPosition":22,"ItemShowType":0,"ItemSize":0,"ItemType":5,"ItemUnit":"","ItemValue":0,"SmsCode":"","SmsSendFilter":false}},{"Key":{"x":23,"y":0},"Value":{"InfoAddress":19,"IsPlusMinusAmbit":false,"IsValidValue":false,"ItemBitPosition":0,"ItemByteOrder":1,"ItemDecimalBits":0,"ItemName":"失压跳闸","ItemPlusMinusAmbit":0,"ItemPosition":23,"ItemShowType":0,"ItemSize":0,"ItemType":5,"ItemUnit":"","ItemValue":0,"SmsCode":"","SmsSendFilter":false}},{"Key":{"x":24,"y":0},"Value":{"InfoAddress":20,"IsPlusMinusAmbit":false,"IsValidValue":false,"ItemBitPosition":0,"ItemByteOrder":1,"ItemDecimalBits":0,"ItemName":"来电合闸","ItemPlusMinusAmbit":0,"ItemPosition":24,"ItemShowType":0,"ItemSize":0,"ItemType":5,"ItemUnit":"","ItemValue":0,"SmsCode":"","SmsSendFilter":false}},{"Key":{"x":25,"y":0},"Value":{"InfoAddress":21,"IsPlusMinusAmbit":false,"IsValidValue":false,"ItemBitPosition":0,"ItemByteOrder":1,"ItemDecimalBits":0,"ItemName":"续费合闸","ItemPlusMinusAmbit":0,"ItemPosition":25,"ItemShowType":0,"ItemSize":0,"ItemType":5,"ItemUnit":"","ItemValue":0,"SmsCode":"","SmsSendFilter":false}},{"Key":{"x":27,"y":0},"Value":{"InfoAddress":23,"IsPlusMinusAmbit":false,"IsValidValue":false,"ItemBitPosition":0,"ItemByteOrder":1,"ItemDecimalBits":0,"ItemName":"非遮断闭锁跳闸","ItemPlusMinusAmbit":0,"ItemPosition":27,"ItemShowType":0,"ItemSize":0,"ItemType":5,"ItemUnit":"","ItemValue":0,"SmsCode":"","SmsSendFilter":false}},{"Key":{"x":28,"y":0},"Value":{"InfoAddress":24,"IsPlusMinusAmbit":false,"IsValidValue":false,"ItemBitPosition":0,"ItemByteOrder":1,"ItemDecimalBits":0,"ItemName":"限时速断","ItemPlusMinusAmbit":0,"ItemPosition":28,"ItemShowType":0,"ItemSize":0,"ItemType":5,"ItemUnit":"","ItemValue":0,"SmsCode":"","SmsSendFilter":false}},{"Key":{"x":29,"y":0},"Value":{"InfoAddress":25,"IsPlusMinusAmbit":false,"IsValidValue":false,"ItemBitPosition":0,"ItemByteOrder":1,"ItemDecimalBits":0,"ItemName":"开关状态","ItemPlusMinusAmbit":0,"ItemPosition":29,"ItemShowType":0,"ItemSize":0,"ItemType":5,"ItemUnit":"","ItemValue":0,"SmsCode":"","SmsSendFilter":false}},{"Key":{"x":30,"y":0},"Value":{"InfoAddress":26,"IsPlusMinusAmbit":false,"IsValidValue":false,"ItemBitPosition":0,"ItemByteOrder":1,"ItemDecimalBits":0,"ItemName":"弹簧未储能","ItemPlusMinusAmbit":0,"ItemPosition":30,"ItemShowType":0,"ItemSize":0,"ItemType":5,"ItemUnit":"","ItemValue":0,"SmsCode":"","SmsSendFilter":false}},{"Key":{"x":32,"y":0},"Value":{"InfoAddress":29,"IsPlusMinusAmbit":false,"IsValidValue":false,"ItemBitPosition":0,"ItemByteOrder":1,"ItemDecimalBits":0,"ItemName":"强制跳闸","ItemPlusMinusAmbit":0,"ItemPosition":32,"ItemShowType":0,"ItemSize":0,"ItemType":5,"ItemUnit":"","ItemValue":0,"SmsCode":"","SmsSendFilter":false}},{"Key":{"x":34,"y":0},"Value":{"InfoAddress":31,"IsPlusMinusAmbit":false,"IsValidValue":false,"ItemBitPosition":0,"ItemByteOrder":1,"ItemDecimalBits":0,"ItemName":"闭锁重合闸","ItemPlusMinusAmbit":0,"ItemPosition":34,"ItemShowType":0,"ItemSize":0,"ItemType":5,"ItemUnit":"","ItemValue":0,"SmsCode":"","SmsSendFilter":false}},{"Key":{"x":35,"y":0},"Value":{"InfoAddress":32,"IsPlusMinusAmbit":false,"IsValidValue":false,"ItemBitPosition":0,"ItemByteOrder":1,"ItemDecimalBits":0,"ItemName":"续费合闸","ItemPlusMinusAmbit":0,"ItemPosition":35,"ItemShowType":0,"ItemSize":0,"ItemType":5,"ItemUnit":"","ItemValue":0,"SmsCode":"","SmsSendFilter":false}}]